adafruit_bitmapsaver.py
adafruit_circuitpython_bitmapsaver-1.3.9.dist-info/licenses/LICENSE
adafruit_circuitpython_bitmapsaver-1.3.9.dist-info/METADATA
adafruit_circuitpython_bitmapsaver-1.3.9.dist-info/WHEEL
adafruit_circuitpython_bitmapsaver-1.3.9.dist-info/top_level.txt
adafruit_circuitpython_bitmapsaver-1.3.9.dist-info/RECORD
