Metadata-Version: 2.4
Name: adafruit-circuitpython-bitmapsaver
Version: 1.3.9
Summary: Save a displayio.Bitmap (and associated displayio.Palette) into a BMP file.
Author-email: Adafruit Industries <circuitpython@adafruit.com>
License: MIT
Project-URL: Homepage, https://github.com/adafruit/Adafruit_CircuitPython_BitmapSaver
Keywords: adafruit,blinka,circuitpython,micropython,bitmapsaver,displayio
Classifier: Intended Audience :: Developers
Classifier: Topic :: Software Development :: Libraries
Classifier: Topic :: Software Development :: Embedded Systems
Classifier: Topic :: System :: Hardware
Classifier: License :: OSI Approved :: MIT License
Classifier: Programming Language :: Python :: 3
License-File: LICENSE
Requires-Dist: Adafruit-Blinka
Provides-Extra: optional
Dynamic: license-file
